LICENSE
README.rst
setup.py
py_mina/__init__.py
py_mina/config.py
py_mina/echo.py
py_mina/state.py
py_mina/utils.py
py_mina.egg-info/PKG-INFO
py_mina.egg-info/SOURCES.txt
py_mina.egg-info/dependency_links.txt
py_mina.egg-info/entry_points.txt
py_mina.egg-info/requires.txt
py_mina.egg-info/top_level.txt
py_mina/cli/__init__.py
py_mina/cli/cli.py
py_mina/cli/commands.py
py_mina/cli/template_generator.py
py_mina/cli/templates.py
py_mina/decorators/__init__.py
py_mina/decorators/deploy.py
py_mina/decorators/setup.py
py_mina/decorators/task.py
py_mina/subtasks/__init__.py
py_mina/subtasks/deploy.py
py_mina/subtasks/git.py
py_mina/subtasks/setup.py