Metadata-Version: 2.1
Name: py-mina
Version: 0.2.6
Summary: Python library for deploying applications on remote server
Home-page: https://github.com/py-mina-deploy/py-mina
Author: Cidevant Von Goethe
Author-email: cidevant@mail.ru
License: MIT
Platform: UNKNOWN
Classifier: Programming Language :: Python
Classifier: Programming Language :: Python :: 2.7
Classifier: Programming Language :: Python :: 3.6
License-File: LICENSE
